demo/__init__.py
demo/mp_demo.py
test/__init__.py
wxmplib/__init__.py
wxmplib/account.py
wxmplib/album.py
wxmplib/browser.py
wxmplib/login.py
wxmplib/main.py
wxmplib/mini_program.py
wxmplib/mp_demo.py
wxmplib/search.py
wxmplib/util.py
wxmplib/wxapp.py
wxmplib/wxtestbase.py
wxmplib-1.1.0.data/data/requirements.txt
wxmplib-1.1.0.dist-info/METADATA
wxmplib-1.1.0.dist-info/WHEEL
wxmplib-1.1.0.dist-info/top_level.txt
wxmplib-1.1.0.dist-info/RECORD
