Metadata-Version: 2.1
Name: wxmplib
Version: 1.1.0
Summary: UNKNOWN
Home-page: UNKNOWN
Author: Tencent
Author-email: UNKNOWN
License: Copyright(c)2010-2019 Tencent All Rights Reserved. 
Platform: UNKNOWN
Requires-Dist: qt4a
Requires-Dist: qt4w
Requires-Dist: chrome-master
